README.rst
outpan.py
setup.cfg
setup.py
outpan.egg-info/PKG-INFO
outpan.egg-info/SOURCES.txt
outpan.egg-info/dependency_links.txt
outpan.egg-info/entry_points.txt
outpan.egg-info/requires.txt
outpan.egg-info/top_level.txt