Metadata-Version: 1.1
Name: outpan
Version: 1.2.0
Summary: Easily use Outpan API to get product info from its barcode
Home-page: https://github.com/bertrandvidal/outpan_api
Author: Bertrand Vidal
Author-email: vidal.bertrand@gmail.com
License: UNKNOWN
Download-URL: https://pypi.python.org/pypi/outpan
Platform: UNKNOWN
Classifier: Intended Audience :: Developers
Classifier: Intended Audience :: Information Technology
Classifier: Operating System :: OS Independent
Classifier: Programming Language :: Python :: 2
Classifier: Programming Language :: Python :: 3
